debug_toolbar/__init__.py
debug_toolbar/_compat.py
debug_toolbar/_stubs.py
debug_toolbar/apps.py
debug_toolbar/decorators.py
debug_toolbar/forms.py
debug_toolbar/middleware.py
debug_toolbar/settings.py
debug_toolbar/toolbar.py
debug_toolbar/urls.py
debug_toolbar/utils.py
debug_toolbar/views.py
debug_toolbar/locale/bg/LC_MESSAGES/django.mo
debug_toolbar/locale/bg/LC_MESSAGES/django.po
debug_toolbar/locale/ca/LC_MESSAGES/django.mo
debug_toolbar/locale/ca/LC_MESSAGES/django.po
debug_toolbar/locale/cs/LC_MESSAGES/django.mo
debug_toolbar/locale/cs/LC_MESSAGES/django.po
debug_toolbar/locale/de/LC_MESSAGES/django.mo
debug_toolbar/locale/de/LC_MESSAGES/django.po
debug_toolbar/locale/en/LC_MESSAGES/django.mo
debug_toolbar/locale/en/LC_MESSAGES/django.po
debug_toolbar/locale/es/LC_MESSAGES/django.mo
debug_toolbar/locale/es/LC_MESSAGES/django.po
debug_toolbar/locale/fa/LC_MESSAGES/django.mo
debug_toolbar/locale/fa/LC_MESSAGES/django.po
debug_toolbar/locale/fi/LC_MESSAGES/django.mo
debug_toolbar/locale/fi/LC_MESSAGES/django.po
debug_toolbar/locale/fr/LC_MESSAGES/django.mo
debug_toolbar/locale/fr/LC_MESSAGES/django.po
debug_toolbar/locale/he/LC_MESSAGES/django.mo
debug_toolbar/locale/he/LC_MESSAGES/django.po
debug_toolbar/locale/id/LC_MESSAGES/django.mo
debug_toolbar/locale/id/LC_MESSAGES/django.po
debug_toolbar/locale/it/LC_MESSAGES/django.mo
debug_toolbar/locale/it/LC_MESSAGES/django.po
debug_toolbar/locale/ja/LC_MESSAGES/django.mo
debug_toolbar/locale/ja/LC_MESSAGES/django.po
debug_toolbar/locale/ko/LC_MESSAGES/django.mo
debug_toolbar/locale/ko/LC_MESSAGES/django.po
debug_toolbar/locale/nl/LC_MESSAGES/django.mo
debug_toolbar/locale/nl/LC_MESSAGES/django.po
debug_toolbar/locale/pl/LC_MESSAGES/django.mo
debug_toolbar/locale/pl/LC_MESSAGES/django.po
debug_toolbar/locale/pt/LC_MESSAGES/django.mo
debug_toolbar/locale/pt/LC_MESSAGES/django.po
debug_toolbar/locale/pt_BR/LC_MESSAGES/django.mo
debug_toolbar/locale/pt_BR/LC_MESSAGES/django.po
django_debug_toolbar-5.0.0.dist-info/METADATA
django_debug_toolbar-5.0.0.dist-info/WHEEL
django_debug_toolbar-5.0.0.dist-info/licenses/LICENSE
django_debug_toolbar-5.0.0.dist-info/RECORD
